IPGeoSearch/__init__.py
IPGeoSearch/search.py
IPGeoSearch-1.0.1.dist-info/LICENSE
IPGeoSearch-1.0.1.dist-info/METADATA
IPGeoSearch-1.0.1.dist-info/WHEEL
IPGeoSearch-1.0.1.dist-info/top_level.txt
IPGeoSearch-1.0.1.dist-info/RECORD
