Metadata-Version: 2.1
Name: IPGeoSearch
Version: 1.0.1
Summary: IPGeo-Search is a python module which allows for easy use of the IPGeo API. It allows both free and paid users to send requests to the server in just one line of code, allowing for customization of how IP lists are loaded.
Home-page: http://ipgeo.azurewebsites.net/
Author: Matthias Rathbun, Cyber Threat Intelligence Lab
Author-email: matthiasrathbun@gmail.com
License: UNKNOWN
Platform: UNKNOWN
Classifier: Programming Language :: Python :: 3.6
Classifier: Programming Language :: Python :: 3.7
Classifier: License :: OSI Approved :: MIT License
Classifier: Operating System :: OS Independent
Requires-Python: >=3.6
Requires-Dist: pandas
